whisper_turbo/__init__.py
whisper_turbo/cli.py
whisper_turbo/transcriber.py
whisper_turbo-0.1.0.dist-info/licenses/LICENSE
whisper_turbo-0.1.0.dist-info/METADATA
whisper_turbo-0.1.0.dist-info/WHEEL
whisper_turbo-0.1.0.dist-info/entry_points.txt
whisper_turbo-0.1.0.dist-info/top_level.txt
whisper_turbo-0.1.0.dist-info/RECORD
