Metadata-Version: 2.4
Name: whisper-turbo
Version: 0.1.0
Summary: High-performance Whisper transcription with Turbo v3 for Apple Silicon
Home-page: https://github.com/xbattlax/whisper-turbo
Author: Nathan Metzger
Author-email: Nathan Metzger <nathan.metzger@voxtria.com>
Maintainer-email: Nathan Metzger <nathan.metzger@voxtria.com>
License: MIT
Project-URL: Homepage, https://github.com/xbattlax/whisper-turbo
Project-URL: Documentation, https://github.com/xbattlax/whisper-turbo#readme
Project-URL: Repository, https://github.com/xbattlax/whisper-turbo.git
Project-URL: Bug Tracker, https://github.com/xbattlax/whisper-turbo/issues
Keywords: whisper,turbo,whisper-turbo,transcription,speech-to-text,mlx,apple-silicon,metal,audio,turbo-v3
Classifier: Development Status :: 4 - Beta
Classifier: Intended Audience :: Developers
Classifier: Topic :: Multimedia :: Sound/Audio :: Speech
Classifier: Topic :: Scientific/Engineering :: Artificial Intelligence
Classifier: License :: OSI Approved :: MIT License
Classifier: Programming Language :: Python :: 3
Classifier: Programming Language :: Python :: 3.8
Classifier: Programming Language :: Python :: 3.9
Classifier: Programming Language :: Python :: 3.10
Classifier: Programming Language :: Python :: 3.11
Classifier: Programming Language :: Python :: 3.12
Classifier: Operating System :: MacOS :: MacOS X
Requires-Python: >=3.8
License-File: LICENSE
Requires-Dist: mlx-whisper>=0.1.0
Requires-Dist: requests>=2.31.0
Requires-Dist: tqdm>=4.66.0
Provides-Extra: dev
Requires-Dist: pytest>=7.4.0; extra == "dev"
Requires-Dist: black>=23.0.0; extra == "dev"
Requires-Dist: flake8>=6.0.0; extra == "dev"
Requires-Dist: build>=0.10.0; extra == "dev"
Requires-Dist: twine>=4.0.0; extra == "dev"
Dynamic: author
Dynamic: home-page
Dynamic: license-file
Dynamic: requires-python
